mantaray_utilities/__init__.py
mantaray_utilities/assert_contracts.py
mantaray_utilities/asset_pretty_print.py
mantaray_utilities/blockchain.py
mantaray_utilities/config.py
mantaray_utilities/general.py
mantaray_utilities/logging.py
mantaray_utilities/superceded.py
mantaray_utilities/user.py
mantaray_utilities-0.2.2.dist-info/LICENSE
mantaray_utilities-0.2.2.dist-info/METADATA
mantaray_utilities-0.2.2.dist-info/WHEEL
mantaray_utilities-0.2.2.dist-info/top_level.txt
mantaray_utilities-0.2.2.dist-info/RECORD
