Metadata-Version: 2.1
Name: mantaray-utilities
Version: 0.2.2
Summary: Utilities sub-package for mantaray
Home-page: UNKNOWN
Author: leucothia
Author-email: devops@oceanprotocol.com
License: UNKNOWN
Platform: UNKNOWN
Classifier: Development Status :: 2 - Pre-Alpha
Classifier: Intended Audience :: Developers
Classifier: License :: OSI Approved :: Apache Software License
Classifier: Natural Language :: English
Classifier: Programming Language :: Python :: 3.7
